appconf/__init__.py
appconf/api.py
appconf/exceptions.py
appconf/main.py
appconf/models.py
appconfig_cli-0.2.0.dist-info/LICENSE.md
appconfig_cli-0.2.0.dist-info/METADATA
appconfig_cli-0.2.0.dist-info/WHEEL
appconfig_cli-0.2.0.dist-info/entry_points.txt
appconfig_cli-0.2.0.dist-info/RECORD
