Metadata-Version: 2.1
Name: appconfig-cli
Version: 0.2.0
Summary: Unofficial CLI tool for working with AWS AppConfig
Home-page: https://github.com/nicksnell/appconfig-cli
License: MIT
Keywords: appconfig,aws,cli,aws-appconfig,appconfig-cli,cli-tool
Author: Nick Snell
Author-email: n@nicksnell.com
Requires-Python: >=3.9,<4.0
Classifier: Development Status :: 3 - Alpha
Classifier: Environment :: Console
Classifier: Intended Audience :: Developers
Classifier: License :: OSI Approved :: MIT License
Classifier: Programming Language :: Python :: 3
Classifier: Programming Language :: Python :: 3.9
Classifier: Programming Language :: Python :: 3.10
Classifier: Programming Language :: Python :: 3.11
Classifier: Programming Language :: Python :: 3.9
Classifier: Topic :: Software Development
Classifier: Topic :: Software Development :: Libraries :: Python Modules
Classifier: Topic :: Utilities
Requires-Dist: boto3 (>=1.27.0,<2.0.0)
Requires-Dist: click (>=8.1.3,<9.0.0)
Requires-Dist: rich (>=13.4.2,<14.0.0)
Project-URL: Repository, https://github.com/nicksnell/appconfig-cli
